sqlaf/__init__.py
sqlaf/config.py
sqlaf/exceptions.py
sqlaf/operators.py
sqlaf/utils.py
sqlaf/fields/__init__.py
sqlaf/fields/base.py
sqlaf/fields/fields.py
sqlaf/fields/interfaces.py
sqlaf/filters/__init__.py
sqlaf/filters/filters.py
sqlaf/filters/interfaces.py
sqlaf-1.1.0.dist-info/METADATA
sqlaf-1.1.0.dist-info/WHEEL
sqlaf-1.1.0.dist-info/licenses/LICENSE
sqlaf-1.1.0.dist-info/RECORD
