Metadata-Version: 2.1
Name: sqlaf
Version: 1.1.0
Summary: Library for transforming query parameters into SQLAlchemy filters in a structured and organised manner.
Project-URL: Homepage, https://github.com/iamstej/sqlaf
Project-URL: Bug Tracker, https://github.com/iamstej/sqlaf/issues
Author: iamstej
License: Copyright 2022 iamstej.com
License-File: LICENSE
Classifier: License :: OSI Approved :: Apache Software License
Classifier: Operating System :: OS Independent
Classifier: Programming Language :: Python :: 3
Requires-Python: >=3.7
